COPYING
LICENSE
MANIFEST.in
README.md
setup.py
examples/get_followers.py
examples/get_followers.py~
examples/public_timeline.py
examples/public_timeline.py~
examples/search.py
examples/show_status.py
examples/show_status.py~
examples/update_status.py
examples/update_status.py~
examples/user_timeline.py
examples/user_timeline.py~
identi/Identi.py
identi/__init__.py
identi/error.py
identi/identica_mappings.py
identi.egg-info/PKG-INFO
identi.egg-info/SOURCES.txt
identi.egg-info/dependency_links.txt
identi.egg-info/requires.txt
identi.egg-info/top_level.txt