Metadata-Version: 1.1
Name: identi
Version: 0.1.3
Summary: An easy to use API library specifically for identi.ca
Home-page: https://github.com/psibi/Identier
Author: Sibi
Author-email: sibi@psibi.in
License: GNU GPLv3
Keywords: identi.ca API library
Platform: UNKNOWN
Classifier: Development Status :: 4 - Beta
Classifier: Intended Audience :: Developers
Classifier: License :: OSI Approved :: GNU General Public License v3 (GPLv3)
Classifier: Topic :: Software Development :: Libraries :: Python Modules
Classifier: Topic :: Communications :: Chat
Classifier: Topic :: Internet
